lambda_utility/__init__.py
lambda_utility/function.py
lambda_utility/image.py
lambda_utility/mp.py
lambda_utility/path.py
lambda_utility/process.py
lambda_utility/s3storage.py
lambda_utility/schema.py
lambda_utility/session.py
lambda_utility/sqs.py
lambda_utility/typedefs.py
lambda_utility/utils.py
lambda_utility/zipper.py
lambda_utility-1.14.0.dist-info/WHEEL
lambda_utility-1.14.0.dist-info/METADATA
lambda_utility-1.14.0.dist-info/RECORD
