Metadata-Version: 2.1
Name: lambda-utility
Version: 1.14.0
Summary: 
Home-page: https://github.com/kakao-webtoon/lambda-utility
Author: Pie
Author-email: pie.pie@kakaoent.com
Maintainer: Pie
Maintainer-email: pie.pie@kakaoent.com
Requires-Python: >=3.7,<4.0
Classifier: Programming Language :: Python :: 3
Classifier: Programming Language :: Python :: 3.7
Classifier: Programming Language :: Python :: 3.8
Classifier: Programming Language :: Python :: 3.9
Requires-Dist: aiobotocore (>=1.3.0,<2.0.0)
Requires-Dist: pydantic (>=1.8.1,<2.0.0)
Project-URL: Repository, https://github.com/kakao-webtoon/lambda-utility
